setup.py
MovingFace.egg-info/PKG-INFO
MovingFace.egg-info/SOURCES.txt
MovingFace.egg-info/dependency_links.txt
MovingFace.egg-info/entry_points.txt
MovingFace.egg-info/top_level.txt
moving_face/__init__.py
moving_face/core.py
moving_face/face.py
moving_face/key.py