Metadata-Version: 1.1
Name: MovingFace
Version: 1.0
Summary: A playing module
Home-page: https://github.com/takoji3/moving_face
Author: Ryo Kawano
Author-email: shonancampus@yahoo.co.jp
License: MIT
Platform: UNKNOWN
Classifier: License :: OSI Approved :: MIT License
Classifier: Programming Language :: Python :: 3
